llama_index/readers/snscrape_twitter/__init__.py
llama_index/readers/snscrape_twitter/base.py
llama_index_readers_snscrape_twitter-0.3.0.dist-info/METADATA
llama_index_readers_snscrape_twitter-0.3.0.dist-info/WHEEL
llama_index_readers_snscrape_twitter-0.3.0.dist-info/RECORD
